xent/__init__.py
xent/py.typed
xent/analysis/__init__.py
xent/analysis/analyze.py
xent/analysis/plot.py
xent/analysis/report.py
xent/benchmark/expand_benchmark.py
xent/benchmark/run_benchmark.py
xent/benchmark/run_haltable.py
xent/cli/analyze.py
xent/cli/cli_util.py
xent/cli/configure.py
xent/cli/main.py
xent/cli/run.py
xent/cli/serve.py
xent/common/__init__.py
xent/common/benchmark_event.py
xent/common/configuration_types.py
xent/common/constants.py
xent/common/errors.py
xent/common/game_discovery.py
xent/common/paths.py
xent/common/token_xent_list.py
xent/common/util.py
xent/common/version.py
xent/common/x_flag.py
xent/common/x_list.py
xent/common/x_string.py
xent/common/xent_event.py
xent/games/Alethiometer.xent
xent/games/Alethiometer_presentation.py
xent/games/Condense.xent
xent/games/Condense_presentation.py
xent/games/Contrast.xent
xent/games/Contrast_presentation.py
xent/games/Horizon.xent
xent/games/Horizon_presentation.py
xent/games/Synthesize.xent
xent/games/Synthesize_presentation.py
xent/games/Two-Ways.xent
xent/games/Two-Ways_presentation.py
xent/games/__init__.py
xent/presentation/executor.py
xent/presentation/sdk.py
xent/runtime/execution.py
xent/runtime/judge.py
xent/runtime/runtime.py
xent/runtime/variables.py
xent/runtime/players/base_player.py
xent/runtime/players/default_players.py
xent/runtime/players/halting_player.py
xent/runtime/players/human_player.py
xent/runtime/players/llm_api_client.py
xent/runtime/players/player_configuration.py
xent/runtime/players/players.py
xent/runtime/players/websocket_player.py
xent/runtime/text_generation/community_archive_generation.py
xent/runtime/text_generation/cosmopedia_generation.py
xent/runtime/text_generation/judge_generation.py
xent/runtime/text_generation/text_generation.py
xent/storage/directory_storage.py
xent/storage/storage_interface.py
xent/web/__init__.py
xent/web/keys_store.py
xent/web/server.py
xent/web/websocket_game_runner.py
xent/web/static/index.html
xent-0.5.0.dist-info/licenses/LICENSE
xent-0.5.0.dist-info/METADATA
xent-0.5.0.dist-info/WHEEL
xent-0.5.0.dist-info/entry_points.txt
xent-0.5.0.dist-info/top_level.txt
xent-0.5.0.dist-info/RECORD
