Metadata-Version: 2.4
Name: xent
Version: 0.5.0
Summary: Xent LLM Benchmarking System
Author-email: Andrew Emil <ace@xent.ai>
License-Expression: MIT
Keywords: llm,benchmark,ai,evaluation
Classifier: Development Status :: 3 - Alpha
Classifier: Intended Audience :: Developers
Classifier: Intended Audience :: Science/Research
Classifier: Intended Audience :: End Users/Desktop
Classifier: Topic :: Scientific/Engineering :: Artificial Intelligence
Classifier: Programming Language :: Python :: 3.12
Requires-Python: <4.0,>=3.12
License-File: LICENSE
Requires-Dist: matplotlib<4.0.0,>=3.10.3
Requires-Dist: anthropic<0.52.0,>=0.51.0
Requires-Dist: ollama<0.5.0,>=0.4.8
Requires-Dist: openai<2.0.0,>=1.81.0
Requires-Dist: torch<3.0.0,>=2.7.0
Requires-Dist: transformers<5.0.0,>=4.52.2
Requires-Dist: accelerate<2.0.0,>=1.7.0
Requires-Dist: click<9.0.0,>=8.2.1
Requires-Dist: google-genai<2.0.0,>=1.17.0
Requires-Dist: typeguard<5.0.0,>=4.4.2
Requires-Dist: hf-xet>=1.1.5
Requires-Dist: fastapi>=0.100.0
Requires-Dist: uvicorn[standard]>=0.23.0
Requires-Dist: platformdirs<5,>=4
Dynamic: license-file
